{
  "project_info": {
    "project_number": "170453963102",
    "project_id": "do-done-doing",
    "storage_bucket": "do-done-doing.appspot.com"
  },
  "client": [
    {
      "client_info": {
        "mobilesdk_app_id": "1:170453963102:android:2548ff8bb8fb581b247fcf",
        "android_client_info": {
          "package_name": "com.example.dodonedoin"
        }
      },
      "oauth_client": [
        {
          "client_id": "170453963102-gn0io0on27au6relnd75d2shssq03lhd.apps.googleusercontent.com",
          "client_type": 1,
          "android_info": {
            "package_name": "com.example.dodonedoin",
            "certificate_hash": "7e30e412685ccc3a82f0ee8d15e20324289e705c"
          }
        },
        {
          "client_id": "170453963102-aigpmcda7c65b20peg0ddo5qnu81und5.apps.googleusercontent.com",
          "client_type": 3
        }
      ],
      "api_key": [
        {
          "current_key": "AIzaSyDcnBap5ZHspCoC2abC6S7Pi2fpZj5CaTw"
        }
      ],
      "services": {
        "appinvite_service": {
          "other_platform_oauth_client": [
            {
              "client_id": "170453963102-aigpmcda7c65b20peg0ddo5qnu81und5.apps.googleusercontent.com",
              "client_type": 3
            }
          ]
        }
      }
    }
  ],
  "configuration_version": "1"
}